rgear/__init__.py
rgear-0.2.0.dist-info/LICENSE
rgear-0.2.0.dist-info/METADATA
rgear-0.2.0.dist-info/WHEEL
rgear-0.2.0.dist-info/entry_points.txt
rgear-0.2.0.dist-info/RECORD
